{
    "sourceFile": "backend/src/rest-resources/routes/api/v1/index.js",
    "activeCommit": 0,
    "commits": [
        {
            "activePatchIndex": 3,
            "patches": [
                {
                    "date": 1753423500202,
                    "content": "Index: \n===================================================================\n--- \n+++ \n"
                },
                {
                    "date": 1753935381825,
                    "content": "Index: \n===================================================================\n--- \n+++ \n@@ -20,9 +20,9 @@\n import { bonusRouter } from './bonus.routes'\n import { notificationRouter } from './notification.routes'\n import { liveChatRouter } from './liveChat.router'\n import { postalCodeRouter } from './postalCode.routes'\n-const authSsoRouter = require('./auth.sso.router');\n+import authSsoRouter from './auth.sso.router'\n \n const v1router = express.Router()\n v1router.use('/vip-tier', vipTierRouter, responseValidationMiddleware({}))\n v1router.use('/bonus', bonusRouter, responseValidationMiddleware({}))\n"
                },
                {
                    "date": 1754045506629,
                    "content": "Index: \n===================================================================\n--- \n+++ \n@@ -1,47 +1,45 @@\n-import express from 'express'\n-\n-import { bannerRouter } from './banner.router'\n-import { casinoRouter } from './casino.router'\n-import { gsoftRouter } from './gsoft.router'\n-import { siteRouter } from './site.router'\n-import { userRouter } from './user.router'\n-import { leaderBoardRouter } from './leaderBoard.routes'\n-// import { documentRouter } from './document.router'\n-// import { affiliateRouter } from './affiliate.router'\n-import { paymentRouter } from './payment.router'\n-// import {  } from './payment.router'\n-// import contextMiddleware from '@src/rest-resources/middlewares/context.middleware'\n-import responseValidationMiddleware from '@src/rest-resources/middlewares/responseValidation.middleware'\n-import { faucetRouter } from './faucet.router'\n-import { packageRouter } from './package.router'\n-import spinWheelRouter from './spinWheel.router'\n-import { ticketRouter } from './ticket.router'\n-import { vipTierRouter } from './vipTier.router'\n-import { bonusRouter } from './bonus.routes'\n-import { notificationRouter } from './notification.routes'\n-import { liveChatRouter } from './liveChat.router'\n-import { postalCodeRouter } from './postalCode.routes'\n-import authSsoRouter from './auth.sso.router'\n-\n-const v1router = express.Router()\n-v1router.use('/vip-tier', vipTierRouter, responseValidationMiddleware({}))\n-v1router.use('/bonus', bonusRouter, responseValidationMiddleware({}))\n-v1router.use('/notification', notificationRouter, responseValidationMiddleware({}))\n-v1router.use('/user', userRouter, responseValidationMiddleware({}))\n-v1router.use('/casino', casinoRouter, responseValidationMiddleware({}))\n-v1router.use('/banner', bannerRouter, responseValidationMiddleware({}))\n-v1router.use('/callback/gsoft', gsoftRouter, responseValidationMiddleware({}))\n-v1router.use('/payment', paymentRouter, responseValidationMiddleware({}))\n-v1router.use('/postal-code', postalCodeRouter, responseValidationMiddleware({}))\n-v1router.use('/package', packageRouter, responseValidationMiddleware({}))\n-v1router.use('/spin-wheel-configuration', spinWheelRouter, responseValidationMiddleware({}))\n-v1router.use('/faucet', faucetRouter, responseValidationMiddleware({}))\n-v1router.use('/ticket', ticketRouter, responseValidationMiddleware({}))\n-v1router.use('/live-chat', liveChatRouter, responseValidationMiddleware({}))\n-v1router.use('/leader-board', leaderBoardRouter, responseValidationMiddleware({}))\n-v1router.use('/auth/sso', authSsoRouter);\n-v1router.use('/', siteRouter, responseValidationMiddleware({}))\n-\n-// v1router.use('/affiliate', requestValidationMiddleware({}), contextMiddleware(false), affiliateRouter, responseValidationMiddleware({}))\n-// Casino Callbacks\n-export default v1router\n+import express from 'express'\r\n+\r\n+import { bannerRouter } from './banner.router'\r\n+import { casinoRouter } from './casino.router'\r\n+import { gsoftRouter } from './gsoft.router'\r\n+import { siteRouter } from './site.router'\r\n+import { userRouter } from './user.router'\r\n+import { leaderBoardRouter } from './leaderBoard.routes'\r\n+// import { documentRouter } from './document.router'\r\n+// import { affiliateRouter } from './affiliate.router'\r\n+import { paymentRouter } from './payment.router'\r\n+// import {  } from './payment.router'\r\n+// import contextMiddleware from '@src/rest-resources/middlewares/context.middleware'\r\n+import responseValidationMiddleware from '@src/rest-resources/middlewares/responseValidation.middleware'\r\n+import { faucetRouter } from './faucet.router'\r\n+import { packageRouter } from './package.router'\r\n+import spinWheelRouter from './spinWheel.router'\r\n+import { ticketRouter } from './ticket.router'\r\n+import { vipTierRouter } from './vipTier.router'\r\n+import { bonusRouter } from './bonus.routes'\r\n+import { notificationRouter } from './notification.routes'\r\n+import { liveChatRouter } from './liveChat.router'\r\n+import { postalCodeRouter } from './postalCode.routes'\r\n+\r\n+const v1router = express.Router()\r\n+v1router.use('/vip-tier', vipTierRouter, responseValidationMiddleware({}))\r\n+v1router.use('/bonus', bonusRouter, responseValidationMiddleware({}))\r\n+v1router.use('/notification', notificationRouter, responseValidationMiddleware({}))\r\n+v1router.use('/user', userRouter, responseValidationMiddleware({}))\r\n+v1router.use('/casino', casinoRouter, responseValidationMiddleware({}))\r\n+v1router.use('/banner', bannerRouter, responseValidationMiddleware({}))\r\n+v1router.use('/callback/gsoft', gsoftRouter, responseValidationMiddleware({}))\r\n+v1router.use('/payment', paymentRouter, responseValidationMiddleware({}))\r\n+v1router.use('/postal-code', postalCodeRouter, responseValidationMiddleware({}))\r\n+v1router.use('/package', packageRouter, responseValidationMiddleware({}))\r\n+v1router.use('/spin-wheel-configuration', spinWheelRouter, responseValidationMiddleware({}))\r\n+v1router.use('/faucet', faucetRouter, responseValidationMiddleware({}))\r\n+v1router.use('/ticket', ticketRouter, responseValidationMiddleware({}))\r\n+v1router.use('/live-chat', liveChatRouter, responseValidationMiddleware({}))\r\n+v1router.use('/leader-board', leaderBoardRouter, responseValidationMiddleware({}))\r\n+v1router.use('/', siteRouter, responseValidationMiddleware({}))\r\n+\r\n+// v1router.use('/affiliate', requestValidationMiddleware({}), contextMiddleware(false), affiliateRouter, responseValidationMiddleware({}))\r\n+// Casino Callbacks\r\n+export default v1router\r\n"
                },
                {
                    "date": 1754046264432,
                    "content": "Index: \n===================================================================\n--- \n+++ \n@@ -20,8 +20,9 @@\n import { bonusRouter } from './bonus.routes'\r\n import { notificationRouter } from './notification.routes'\r\n import { liveChatRouter } from './liveChat.router'\r\n import { postalCodeRouter } from './postalCode.routes'\r\n+import authSsoRouter from './auth.sso.router'\r\n \r\n const v1router = express.Router()\r\n v1router.use('/vip-tier', vipTierRouter, responseValidationMiddleware({}))\r\n v1router.use('/bonus', bonusRouter, responseValidationMiddleware({}))\r\n@@ -37,8 +38,9 @@\n v1router.use('/faucet', faucetRouter, responseValidationMiddleware({}))\r\n v1router.use('/ticket', ticketRouter, responseValidationMiddleware({}))\r\n v1router.use('/live-chat', liveChatRouter, responseValidationMiddleware({}))\r\n v1router.use('/leader-board', leaderBoardRouter, responseValidationMiddleware({}))\r\n+v1router.use('/auth/sso', authSsoRouter);\r\n v1router.use('/', siteRouter, responseValidationMiddleware({}))\r\n \r\n // v1router.use('/affiliate', requestValidationMiddleware({}), contextMiddleware(false), affiliateRouter, responseValidationMiddleware({}))\r\n // Casino Callbacks\r\n"
                }
            ],
            "date": 1753423500202,
            "name": "Commit-0",
            "content": "import express from 'express'\n\nimport { bannerRouter } from './banner.router'\nimport { casinoRouter } from './casino.router'\nimport { gsoftRouter } from './gsoft.router'\nimport { siteRouter } from './site.router'\nimport { userRouter } from './user.router'\nimport { leaderBoardRouter } from './leaderBoard.routes'\n// import { documentRouter } from './document.router'\n// import { affiliateRouter } from './affiliate.router'\nimport { paymentRouter } from './payment.router'\n// import {  } from './payment.router'\n// import contextMiddleware from '@src/rest-resources/middlewares/context.middleware'\nimport responseValidationMiddleware from '@src/rest-resources/middlewares/responseValidation.middleware'\nimport { faucetRouter } from './faucet.router'\nimport { packageRouter } from './package.router'\nimport spinWheelRouter from './spinWheel.router'\nimport { ticketRouter } from './ticket.router'\nimport { vipTierRouter } from './vipTier.router'\nimport { bonusRouter } from './bonus.routes'\nimport { notificationRouter } from './notification.routes'\nimport { liveChatRouter } from './liveChat.router'\nimport { postalCodeRouter } from './postalCode.routes'\nconst authSsoRouter = require('./auth.sso.router');\n\nconst v1router = express.Router()\nv1router.use('/vip-tier', vipTierRouter, responseValidationMiddleware({}))\nv1router.use('/bonus', bonusRouter, responseValidationMiddleware({}))\nv1router.use('/notification', notificationRouter, responseValidationMiddleware({}))\nv1router.use('/user', userRouter, responseValidationMiddleware({}))\nv1router.use('/casino', casinoRouter, responseValidationMiddleware({}))\nv1router.use('/banner', bannerRouter, responseValidationMiddleware({}))\nv1router.use('/callback/gsoft', gsoftRouter, responseValidationMiddleware({}))\nv1router.use('/payment', paymentRouter, responseValidationMiddleware({}))\nv1router.use('/postal-code', postalCodeRouter, responseValidationMiddleware({}))\nv1router.use('/package', packageRouter, responseValidationMiddleware({}))\nv1router.use('/spin-wheel-configuration', spinWheelRouter, responseValidationMiddleware({}))\nv1router.use('/faucet', faucetRouter, responseValidationMiddleware({}))\nv1router.use('/ticket', ticketRouter, responseValidationMiddleware({}))\nv1router.use('/live-chat', liveChatRouter, responseValidationMiddleware({}))\nv1router.use('/leader-board', leaderBoardRouter, responseValidationMiddleware({}))\nv1router.use('/auth/sso', authSsoRouter);\nv1router.use('/', siteRouter, responseValidationMiddleware({}))\n\n// v1router.use('/affiliate', requestValidationMiddleware({}), contextMiddleware(false), affiliateRouter, responseValidationMiddleware({}))\n// Casino Callbacks\nexport default v1router\n"
        }
    ]
}